tesswcs/__init__.py
tesswcs/data/TESS_wcs_M.json.bz2
tesswcs/data/TESS_wcs_Ms.json.bz2
tesswcs/data/TESS_wcs_data.json.bz2
tesswcs/data/TESS_wcs_offset_weights.json.bz2
tesswcs/data/TESS_wcs_sip.json.bz2
tesswcs/data/TESS_wcs_xcent.json.bz2
tesswcs/data/TESS_wcs_xs.json.bz2
tesswcs/data/TESS_wcs_ycent.json.bz2
tesswcs/data/TESS_wcs_ys.json.bz2
tesswcs/data/pointings.csv
tesswcs/database.py
tesswcs/locate.py
tesswcs/tesswcs.py
tesswcs/utils.py
tesswcs-1.8.4.dist-info/METADATA
tesswcs-1.8.4.dist-info/WHEEL
tesswcs-1.8.4.dist-info/licenses/LICENSE
tesswcs-1.8.4.dist-info/RECORD
