Metadata-Version: 2.4
Name: tesswcs
Version: 1.8.4
Summary: 
License-File: LICENSE
Author: Christina Hedges
Author-email: christina.l.hedges@nasa.gov
Requires-Python: >=3.9,<4.0
Classifier: Programming Language :: Python :: 3
Classifier: Programming Language :: Python :: 3.9
Classifier: Programming Language :: Python :: 3.10
Classifier: Programming Language :: Python :: 3.11
Classifier: Programming Language :: Python :: 3.12
Classifier: Programming Language :: Python :: 3.13
Classifier: Programming Language :: Python :: 3.14
Provides-Extra: database
Requires-Dist: astropy (>=5.0)
Requires-Dist: astroquery (>=0.4.9)
Requires-Dist: matplotlib (>=3.8.2)
Requires-Dist: pandas (>=2.2.3,<3.0.0)
Requires-Dist: tesscube (>=1.2.0) ; extra == "database"
Requires-Dist: tqdm (>=4.66.1)
